bottt.py
bottt-0.0.1.dist-info/WHEEL
bottt-0.0.1.dist-info/METADATA
bottt-0.0.1.dist-info/RECORD
