Metadata-Version: 2.1
Name: bottt
Version: 0.0.1
Summary: bottt
Author: Olli Paloviita
Classifier: License :: OSI Approved :: MIT License
